MANIFEST.in
VERSION
requirements.txt
setup.cfg
setup.py
botilab_init_ubuntu_server/__init__.py
botilab_init_ubuntu_server/fabfile.py
botilab_init_ubuntu_server.egg-info/PKG-INFO
botilab_init_ubuntu_server.egg-info/SOURCES.txt
botilab_init_ubuntu_server.egg-info/dependency_links.txt
botilab_init_ubuntu_server.egg-info/requires.txt
botilab_init_ubuntu_server.egg-info/top_level.txt
botilab_init_ubuntu_server/scripts/__init__.py
botilab_init_ubuntu_server/scripts/configure_auto_updates.py
botilab_init_ubuntu_server/scripts/configure_ssh_connection.py
botilab_init_ubuntu_server/scripts/create_sudo_user.py
botilab_init_ubuntu_server/scripts/create_swap.py
botilab_init_ubuntu_server/scripts/fab_utils.py
venv/lib/python3.6/site-packages/asn1crypto/__init__.py
venv/lib/python3.6/site-packages/asn1crypto/_perf/__init__.py
venv/lib/python3.6/site-packages/cffi/__init__.py
venv/lib/python3.6/site-packages/cryptography/__init__.py
venv/lib/python3.6/site-packages/cryptography/hazmat/__init__.py
venv/lib/python3.6/site-packages/cryptography/hazmat/backends/__init__.py
venv/lib/python3.6/site-packages/cryptography/hazmat/backends/commoncrypto/__init__.py
venv/lib/python3.6/site-packages/cryptography/hazmat/backends/openssl/__init__.py
venv/lib/python3.6/site-packages/cryptography/hazmat/bindings/__init__.py
venv/lib/python3.6/site-packages/cryptography/hazmat/bindings/commoncrypto/__init__.py
venv/lib/python3.6/site-packages/cryptography/hazmat/bindings/openssl/__init__.py
venv/lib/python3.6/site-packages/cryptography/hazmat/primitives/__init__.py
venv/lib/python3.6/site-packages/cryptography/hazmat/primitives/asymmetric/__init__.py
venv/lib/python3.6/site-packages/cryptography/hazmat/primitives/ciphers/__init__.py
venv/lib/python3.6/site-packages/cryptography/hazmat/primitives/interfaces/__init__.py
venv/lib/python3.6/site-packages/cryptography/hazmat/primitives/kdf/__init__.py
venv/lib/python3.6/site-packages/cryptography/hazmat/primitives/twofactor/__init__.py
venv/lib/python3.6/site-packages/cryptography/x509/__init__.py
venv/lib/python3.6/site-packages/fabfile/__init__.py
venv/lib/python3.6/site-packages/fabric/__init__.py
venv/lib/python3.6/site-packages/fabric/contrib/__init__.py
