Metadata-Version: 1.0
Name: botilab-init-ubuntu-server
Version: 1.2.0
Summary: Init botilab ubuntu server
Home-page: UNKNOWN
Author: Pascal Ekouaghe
Author-email: ekougs@gmail.com
License: MIT
Platform: UNKNOWN
